k3stubproxy/__init__.py
k3stubproxy/_version.py
k3stubproxy/client.py
k3stubproxy/server.py
k3stubproxy/stub_generator.py
k3stubproxy/stub_target_generator.py
k3stubproxy/c_stub/__init__.py
k3stubproxy/main/__init__.py
k3stubproxy/main/dump_function_definition.py
k3stubproxy/main/stub_target_generator.py
k3stubproxy/main/stubgenerator.py
k3stubproxy-0.2.4.dist-info/LICENSE
k3stubproxy-0.2.4.dist-info/METADATA
k3stubproxy-0.2.4.dist-info/WHEEL
k3stubproxy-0.2.4.dist-info/entry_points.txt
k3stubproxy-0.2.4.dist-info/top_level.txt
k3stubproxy-0.2.4.dist-info/RECORD
