Metadata-Version: 2.1
Name: k3stubproxy
Version: 0.2.4
Summary: A library that simplifies proxying stub functions in c
Home-page: UNKNOWN
Author: Joachim Kestner
Author-email: joachim.kestner@khoch3.de
License: UNKNOWN
Platform: UNKNOWN
Classifier: Programming Language :: Python :: 3
Classifier: License :: OSI Approved :: MIT License
Classifier: Operating System :: OS Independent
Requires-Python: ~=3.6
Requires-Dist: k3logging (==0.1)
Requires-Dist: k3process (==0.4)
